mx06/__init__.py
mx06/_version.py
mx06/env.py
mx06/py.typed
mx06/vclient.py
mx06/vlocalcluster.py
mx06/vpandas.py
mx06/bin/__init__.py
mx06/bin/build-conda-vdf-env
mx06/bin/virtual_dataframe-all.yml
mx06/bin/virtual_dataframe-cudf.yml
mx06/bin/virtual_dataframe-dask-local.yml
mx06/bin/virtual_dataframe-dask.yml
mx06/bin/virtual_dataframe-dask_cudf-local.yml
mx06/bin/virtual_dataframe-dask_cudf.yml
mx06/bin/virtual_dataframe-dask_modin-local.yml
mx06/bin/virtual_dataframe-dask_modin.yml
mx06/bin/virtual_dataframe-modin.yml
mx06/bin/virtual_dataframe-pandas.yml
mx06/bin/virtual_dataframe-pyspark-local.yml
mx06/bin/virtual_dataframe-pyspark.yml
mx06/bin/virtual_dataframe-pyspark_gpu-local.yml
mx06/bin/virtual_dataframe-pyspark_gpu.yml
mx06/numpy/__init__.py
mx07-0.2.dev0.dist-info/LICENSE.txt
mx07-0.2.dev0.dist-info/METADATA
mx07-0.2.dev0.dist-info/WHEEL
mx07-0.2.dev0.dist-info/entry_points.txt
mx07-0.2.dev0.dist-info/top_level.txt
mx07-0.2.dev0.dist-info/RECORD
